tvsleep/__init__.py
tvsleep/gui.py
tvsleep/main.py
tvsleep/tvsleep.py
tvsleep/util.py
tvsleep-0.4.data/scripts/tvsleep
tvsleep-0.4.dist-info/LICENSE
tvsleep-0.4.dist-info/METADATA
tvsleep-0.4.dist-info/WHEEL
tvsleep-0.4.dist-info/top_level.txt
tvsleep-0.4.dist-info/RECORD
