Metadata-Version: 2.1
Name: tvsleep
Version: 0.4
Summary: put your computer to sleep after a delay
Home-page: https://github.com/tristanmkernan/tvsleep
Author: tristank
Author-email: tristanmkernan@gmail.com
License: gplv3
Platform: UNKNOWN
